{
  "name": "Caroline Sinders",
  "slug": "caroline-sinders",
  "description": "<p><strong>Caroline Sinders</strong> is an award-winning critical designer, researcher, and artist.  They’re the founder of the human rights and design lab Convocation Research.</p>",
  "descriptionPlainText": "Caroline Sinders is an award-winning critical designer, researcher, and artist.  They’re the founder of the human rights and design lab Convocation Research.",
  "photo": "/uploads/Caroline_Sinders_jpg_96ac18fe07.webp",
  "photoAlt": "Caroline Sinders",
  "linkedinUrl": "https://www.linkedin.com/in/carosine/",
  "grantReportUrl": null,
  "order": 0
}